{
  "id": "xamanismo",
  "phrases": [
    {
      "text": "Caminhe sobre a terra com leveza, pois ela é emprestada das gerações futuras.",
      "reference": "Sabedoria Ancestral"
    },
    {
      "text": "A Mãe Terra não nos pertence; somos nós que pertencemos a ela.",
      "reference": "Provérbio dos povos originários"
    },
    {
      "text": "Escute o vento, pois nele sopram as vozes dos antepassados.",
      "reference": "Tradição Xamânica"
    },
    {
      "text": "Tudo o que fazemos à teia da vida, fazemos a nós mesmos.",
      "reference": "Sabedoria Ancestral"
    },
    {
      "text": "O rio não corre apressado, ainda assim sempre chega ao mar.",
      "reference": "Sabedoria dos antigos"
    },
    {
      "text": "Cada árvore é um ancião de raízes profundas; aprenda com seu silêncio.",
      "reference": "Tradição Xamânica"
    },
    {
      "text": "O fogo ensina que a luz nasce do que se entrega às chamas.",
      "reference": "Sabedoria Ancestral"
    },
    {
      "text": "Quem honra os quatro ventos encontra direção em qualquer caminho.",
      "reference": "Provérbio dos povos originários"
    },
    {
      "text": "A cura começa quando reconciliamos o corpo com o espírito da terra.",
      "reference": "Tradição Xamânica"
    },
    {
      "text": "Antes de falar, deixe que o coração escute o que a natureza já sabe.",
      "reference": "Sabedoria dos antigos"
    },
    {
      "text": "O sol nasce todos os dias para lembrar que sempre há um recomeço.",
      "reference": "Sabedoria Ancestral"
    },
    {
      "text": "Não há solidão para quem caminha junto aos animais de poder.",
      "reference": "Tradição Xamânica"
    },
    {
      "text": "A água lembra de todos os caminhos por onde passou; seja como a água.",
      "reference": "Provérbio dos povos originários"
    },
    {
      "text": "Plante hoje a semente cuja sombra você talvez nunca veja.",
      "reference": "Sabedoria dos antigos"
    },
    {
      "text": "Os ancestrais vivem em nosso sangue, em nossos sonhos e em nossas mãos.",
      "reference": "Tradição Xamânica"
    },
    {
      "text": "O que é dado à terra com gratidão volta multiplicado.",
      "reference": "Sabedoria Ancestral"
    },
    {
      "text": "Aprenda a paciência da montanha e a coragem do rio.",
      "reference": "Provérbio dos povos originários"
    },
    {
      "text": "A noite não é o fim da luz, apenas o descanso do sol.",
      "reference": "Sabedoria dos antigos"
    },
    {
      "text": "Cada animal que cruza seu caminho traz uma mensagem do espírito.",
      "reference": "Tradição Xamânica"
    },
    {
      "text": "Honre o alimento, pois nele há a vida de muitos seres.",
      "reference": "Sabedoria Ancestral"
    },
    {
      "text": "A terra cura os pés descalços de quem a respeita.",
      "reference": "Provérbio dos povos originários"
    },
    {
      "text": "Sonhar é caminhar por trilhas que os olhos abertos não enxergam.",
      "reference": "Tradição Xamânica"
    },
    {
      "text": "O equilíbrio não é ficar parado, mas dançar com os ciclos da vida.",
      "reference": "Sabedoria dos antigos"
    },
    {
      "text": "Respeite a aranha, pois ela tece a teia que conecta todas as coisas.",
      "reference": "Tradição Xamânica"
    },
    {
      "text": "Quem agradece pela chuva também aprende a agradecer pela seca.",
      "reference": "Sabedoria Ancestral"
    },
    {
      "text": "As estrelas são as fogueiras dos ancestrais que velam por nós.",
      "reference": "Provérbio dos povos originários"
    },
    {
      "text": "A floresta fala baixo; cale-se para ouvi-la.",
      "reference": "Sabedoria dos antigos"
    },
    {
      "text": "Toda ferida carrega em si a medicina para sua própria cura.",
      "reference": "Tradição Xamânica"
    },
    {
      "text": "O urso ensina que há força no recolhimento e na quietude.",
      "reference": "Sabedoria Ancestral"
    },
    {
      "text": "A águia voa alto para enxergar o todo; aprenda a olhar de longe.",
      "reference": "Provérbio dos povos originários"
    },
    {
      "text": "O que se colhe na vida foi semeado pelas mãos dos que vieram antes.",
      "reference": "Sabedoria dos antigos"
    },
    {
      "text": "Seja como o bambu: dobre-se com o vento e não se quebre.",
      "reference": "Tradição Xamânica"
    },
    {
      "text": "A terra perdoa, ensina e recebe a todos sem distinção.",
      "reference": "Sabedoria Ancestral"
    },
    {
      "text": "Os quatro elementos vivem dentro de você: terra, água, fogo e ar.",
      "reference": "Tradição Xamânica"
    },
    {
      "text": "Quem fala demais cobre o som dos espíritos com a própria voz.",
      "reference": "Provérbio dos povos originários"
    },
    {
      "text": "A semente confia na escuridão da terra antes de buscar a luz.",
      "reference": "Sabedoria dos antigos"
    },
    {
      "text": "O lobo caminha sozinho, mas nunca esquece sua matilha.",
      "reference": "Tradição Xamânica"
    },
    {
      "text": "Honre seus mais velhos, pois eles guardam os mapas do caminho.",
      "reference": "Sabedoria Ancestral"
    },
    {
      "text": "A lua governa as marés e também os ciclos do coração.",
      "reference": "Provérbio dos povos originários"
    },
    {
      "text": "Caminhe em beleza e a beleza caminhará diante de você.",
      "reference": "Sabedoria dos antigos"
    },
    {
      "text": "O fogo sagrado não consome: ele transforma.",
      "reference": "Tradição Xamânica"
    },
    {
      "text": "Cada amanhecer é uma oração que a terra repete sem cansar.",
      "reference": "Sabedoria Ancestral"
    },
    {
      "text": "O beija-flor ensina que doçura e leveza também são forças.",
      "reference": "Provérbio dos povos originários"
    },
    {
      "text": "Não tome da floresta mais do que precisa para viver.",
      "reference": "Sabedoria dos antigos"
    },
    {
      "text": "A serpente troca de pele para que a vida continue; saiba renascer.",
      "reference": "Tradição Xamânica"
    },
    {
      "text": "O coração que escuta a terra nunca se perde no caminho.",
      "reference": "Sabedoria Ancestral"
    },
    {
      "text": "A tartaruga carrega o mundo nas costas e ensina a andar devagar.",
      "reference": "Provérbio dos povos originários"
    },
    {
      "text": "Toda dor que se atravessa com gratidão se torna sabedoria.",
      "reference": "Sabedoria dos antigos"
    },
    {
      "text": "O canto dos pássaros é a primeira reza de cada manhã.",
      "reference": "Tradição Xamânica"
    },
    {
      "text": "Aquele que respeita a aranha, o cervo e o falcão respeita a si mesmo.",
      "reference": "Sabedoria Ancestral"
    },
    {
      "text": "A terra é generosa com quem caminha com o coração aberto.",
      "reference": "Provérbio dos povos originários"
    },
    {
      "text": "O silêncio do mato cura mais do que mil palavras.",
      "reference": "Sabedoria dos antigos"
    },
    {
      "text": "Cada pedra guarda a memória de milhares de invernos.",
      "reference": "Tradição Xamânica"
    },
    {
      "text": "O verdadeiro guerreiro luta para que a vida floresça, não para destruir.",
      "reference": "Sabedoria Ancestral"
    },
    {
      "text": "Respeite o tempo das estações; nada na natureza tem pressa.",
      "reference": "Provérbio dos povos originários"
    },
    {
      "text": "A medicina mais antiga é a gratidão pelo simples ato de respirar.",
      "reference": "Sabedoria dos antigos"
    },
    {
      "text": "O cervo move-se com gentileza e mostra o caminho da delicadeza.",
      "reference": "Tradição Xamânica"
    },
    {
      "text": "Quem cuida da nascente cuida de todos os rios que dela nascem.",
      "reference": "Sabedoria Ancestral"
    },
    {
      "text": "Os sonhos são portas; o xamã apenas aprende a atravessá-las.",
      "reference": "Tradição Xamânica"
    },
    {
      "text": "Devolva à terra com a mesma reverência com que dela recebe.",
      "reference": "Provérbio dos povos originários"
    },
    {
      "text": "A fogueira reúne o círculo; no círculo todos são iguais.",
      "reference": "Sabedoria dos antigos"
    },
    {
      "text": "O coruja enxerga na escuridão o que o orgulho não deixa ver.",
      "reference": "Tradição Xamânica"
    },
    {
      "text": "Honre a chuva que cai, pois ela é a dança do céu com a terra.",
      "reference": "Sabedoria Ancestral"
    },
    {
      "text": "Tudo que vive merece um lugar sob o mesmo céu.",
      "reference": "Provérbio dos povos originários"
    },
    {
      "text": "A raiz não inveja a flor; cada um cumpre seu papel na árvore da vida.",
      "reference": "Sabedoria dos antigos"
    },
    {
      "text": "O espírito da terra fala através do trovão, do orvalho e do silêncio.",
      "reference": "Tradição Xamânica"
    },
    {
      "text": "Caminhe com gratidão e cada passo será uma oferenda.",
      "reference": "Sabedoria Ancestral"
    },
    {
      "text": "A força do rio está em nunca parar de fluir.",
      "reference": "Provérbio dos povos originários"
    },
    {
      "text": "O verdadeiro saber não se acumula: ele se compartilha ao redor do fogo.",
      "reference": "Sabedoria dos antigos"
    },
    {
      "text": "Quando a alma adoece, é à natureza que se deve voltar.",
      "reference": "Tradição Xamânica"
    },
    {
      "text": "O bisão ensina que a abundância vem de honrar o que se recebe.",
      "reference": "Sabedoria Ancestral"
    },
    {
      "text": "Antes de cortar a árvore, agradeça por toda a sombra que ela ofereceu.",
      "reference": "Provérbio dos povos originários"
    },
    {
      "text": "A escuta é a primeira medicina do espírito.",
      "reference": "Sabedoria dos antigos"
    },
    {
      "text": "O coração humano e o coração da terra batem no mesmo ritmo.",
      "reference": "Tradição Xamânica"
    },
    {
      "text": "Onde há respeito pela vida, ali floresce a cura.",
      "reference": "Sabedoria Ancestral"
    },
    {
      "text": "A formiga ensina que a pequenez não impede grandes obras.",
      "reference": "Provérbio dos povos originários"
    },
    {
      "text": "O sol não escolhe sobre quem brilhar; seja generoso como ele.",
      "reference": "Sabedoria dos antigos"
    },
    {
      "text": "Os ancestrais sussurram nas folhas para quem sabe ficar em silêncio.",
      "reference": "Tradição Xamânica"
    },
    {
      "text": "A vida é um círculo: nascimento, crescimento, descanso e retorno.",
      "reference": "Sabedoria Ancestral"
    },
    {
      "text": "Respeite a teia, pois cada fio sustenta o próximo.",
      "reference": "Provérbio dos povos originários"
    },
    {
      "text": "A terra molhada lembra que toda lágrima também alimenta a vida.",
      "reference": "Sabedoria dos antigos"
    },
    {
      "text": "O falcão ensina a focar no que importa e deixar passar o resto.",
      "reference": "Tradição Xamânica"
    },
    {
      "text": "Quem caminha com os pés na terra e os olhos no céu não se perde.",
      "reference": "Sabedoria Ancestral"
    },
    {
      "text": "Cada estação carrega seu próprio remédio e sua própria lição.",
      "reference": "Provérbio dos povos originários"
    },
    {
      "text": "O fogo do coração aquece sem precisar queimar.",
      "reference": "Sabedoria dos antigos"
    },
    {
      "text": "A floresta dá frutos a quem sabe esperar com paciência.",
      "reference": "Tradição Xamânica"
    },
    {
      "text": "Honre o ar que respira, pois ele já passou por incontáveis seres.",
      "reference": "Sabedoria Ancestral"
    },
    {
      "text": "O caminho do equilíbrio passa por receber e por devolver.",
      "reference": "Provérbio dos povos originários"
    },
    {
      "text": "A semente do cedro carrega dentro de si toda a floresta.",
      "reference": "Sabedoria dos antigos"
    },
    {
      "text": "O xamã não cura: ele lembra a alma de sua própria força.",
      "reference": "Tradição Xamânica"
    },
    {
      "text": "Agradeça à manhã antes de pedir qualquer coisa ao dia.",
      "reference": "Sabedoria Ancestral"
    },
    {
      "text": "O cavalo ensina a confiar no movimento e na liberdade.",
      "reference": "Provérbio dos povos originários"
    },
    {
      "text": "Quem respeita o ciclo da lua aprende a respeitar seu próprio tempo.",
      "reference": "Sabedoria dos antigos"
    },
    {
      "text": "A terra guarda em silêncio as histórias de todos os povos.",
      "reference": "Tradição Xamânica"
    },
    {
      "text": "O orvalho da manhã é a bênção que a noite deixa para a terra.",
      "reference": "Sabedoria Ancestral"
    },
    {
      "text": "Caminhe de mãos vazias e o espírito as encherá de presentes.",
      "reference": "Provérbio dos povos originários"
    },
    {
      "text": "O peixe não conhece a sede; viva em harmonia com o que o sustenta.",
      "reference": "Sabedoria dos antigos"
    },
    {
      "text": "Toda criança é semente de ancião; cuide bem de suas raízes.",
      "reference": "Tradição Xamânica"
    },
    {
      "text": "A gratidão é o cântico que a terra reconhece em qualquer língua.",
      "reference": "Sabedoria Ancestral"
    },
    {
      "text": "O raposa ensina que a astúcia também é forma de respeito ao caminho.",
      "reference": "Provérbio dos povos originários"
    },
    {
      "text": "Quem alimenta o ódio queima a própria floresta interior.",
      "reference": "Sabedoria dos antigos"
    },
    {
      "text": "O tambor imita o coração da Mãe Terra para que dancemos com ela.",
      "reference": "Tradição Xamânica"
    },
    {
      "text": "Respeite a noite, pois é nela que as sementes do sonho germinam.",
      "reference": "Sabedoria Ancestral"
    },
    {
      "text": "A montanha não corre atrás das nuvens; deixa que elas venham a ela.",
      "reference": "Provérbio dos povos originários"
    },
    {
      "text": "Cure-se na natureza e você levará a cura aonde for.",
      "reference": "Sabedoria dos antigos"
    },
    {
      "text": "O veado bebe na fonte sem turvá-la; tome apenas o necessário.",
      "reference": "Tradição Xamânica"
    },
    {
      "text": "Os mortos não partem: tornam-se vento, raiz e estrela.",
      "reference": "Sabedoria Ancestral"
    },
    {
      "text": "A folha que cai alimenta a árvore que a deixou ir.",
      "reference": "Provérbio dos povos originários"
    },
    {
      "text": "O verdadeiro caminho não se conquista; ele se descobre caminhando.",
      "reference": "Sabedoria dos antigos"
    },
    {
      "text": "A baleia guarda as canções mais antigas do mundo nas profundezas.",
      "reference": "Tradição Xamânica"
    },
    {
      "text": "Honre o círculo da vida e ele te receberá em todas as estações.",
      "reference": "Sabedoria Ancestral"
    },
    {
      "text": "O sopro do vento e o teu sopro são feitos do mesmo ar sagrado.",
      "reference": "Provérbio dos povos originários"
    },
    {
      "text": "Quem caminha em paz com a terra dorme em paz sob as estrelas.",
      "reference": "Sabedoria dos antigos"
    },
    {
      "text": "A pomba ensina que a serenidade também é uma forma de força.",
      "reference": "Tradição Xamânica"
    },
    {
      "text": "Toda colheita pede que se guarde uma semente para a terra.",
      "reference": "Sabedoria Ancestral"
    },
    {
      "text": "O espírito da água pede que se beba com reverência e gratidão.",
      "reference": "Provérbio dos povos originários"
    },
    {
      "text": "A Roda de Cura tem quatro direções, e cada uma traz um dom: do leste a clareza, do sul a confiança, do oeste a introspecção, do norte a sabedoria.",
      "reference": "Sabedoria da Roda Medicinal"
    },
    {
      "text": "Todo ser tem um animal de poder que caminha ao seu lado. Aprende com a sua força sem deixar de honrar a tua.",
      "reference": "Sabedoria dos Animais de Poder"
    },
    {
      "text": "O canto de cura abre o que as palavras fecham. Onde a razão não alcança, a voz e o tambor curam.",
      "reference": "Canto de Cura"
    },
    {
      "text": "A Mãe Terra empresta, não dá: tudo o que tomas dela, devolve com gratidão e cuidado.",
      "reference": "Sabedoria da Mãe Terra"
    },
    {
      "text": "O tambor é o coração da Terra batendo. Quando o escutas, lembras de que pertences a algo maior.",
      "reference": "Tradição Xamânica"
    },
    {
      "text": "Os quatro ventos carregam mensagens: aprende a parar e escutar o que a natureza sussurra.",
      "reference": "Sabedoria dos Quatro Ventos"
    },
    {
      "text": "Honra os antepassados, pois caminham contigo. Quem esquece a raiz seca antes do tempo.",
      "reference": "Sabedoria Ancestral"
    },
    {
      "text": "A doença começa muito antes do corpo: cura primeiro a alma e o resto encontra o seu caminho.",
      "reference": "Tradição Xamânica"
    },
    {
      "text": "A fumaça sagrada limpa o que os olhos não veem. Defuma a tua casa e o teu coração.",
      "reference": "Tradição Xamânica"
    },
    {
      "text": "O xamã não cura: ele abre a porta para que a própria pessoa se cure. O poder sempre esteve dentro de ti.",
      "reference": "Sabedoria Ancestral"
    },
    {
      "text": "Pede licença ao entrar na mata, ao colher a planta, ao beber da fonte. Tudo é vivo, tudo merece respeito.",
      "reference": "Provérbio dos povos originários"
    },
    {
      "text": "A roda não tem começo nem fim, como a vida: o que parece morte é apenas o giro para um novo nascer.",
      "reference": "Sabedoria da Roda Medicinal"
    }
  ]
}